{
	"name": "json",
	"properties": {
		"linkedServiceName": {
			"referenceName": "datalake",
			"type": "LinkedServiceReference"
		},
		"parameters": {
			"pipelineid": {
				"type": "string"
			}
		},
		"annotations": [],
		"type": "Json",
		"typeProperties": {
			"location": {
				"type": "AzureBlobFSLocation",
				"fileName": {
					"value": "@concat('customers_', dataset().pipelineid, '.json')",
					"type": "Expression"
				},
				"folderPath": "rob",
				"fileSystem": "demo"
			}
		},
		"schema": {}
	}
}